[{"name":"三棵松电竞网咖","address":"龚家坪北路209号(理工大东门)1958文创广场院内","phone":"电话:15693871106"},{"name":"悟空·电竞生活馆","address":"皋兰路街道麦积山路詹家拐子150号第1-2层","phone":"电话:0931-4635501"},{"name":"遇见电竞(火车站店)","address":"火东路338号","phone":"电话:17309424858"},{"name":"强力网咖","address":"世纪大道长风医院北100米","phone":""},{"name":"昕晴网吧","address":"西固中街66号","phone":"电话:18919873040"},{"name":"海豚电竞(卓威体验店)","address":"敦煌路349号万辉国际广场1号楼A区三层第1室","phone":"电话:18293102220"},{"name":"信达电竞中心","address":"宝兴庄68号","phone":"电话:15117229223"},{"name":"时光网咖(白龙江街店)","address":"白龙江街","phone":"电话:0931-6650115/18701036606"},{"name":"兰州新区东虎网咖","address":"鹏博商业风情街s1区4楼415号","phone":"电话:18809469095"},{"name":"乔木电子竞技馆","address":"和平大道98号301铺","phone":"电话:17339813942"},{"name":"顶级网咖","address":"桃海商业广场步行街二楼","phone":"电话:13510477460"},{"name":"海豚电竞(卓威体验店)","address":"敦煌路349号万辉国际广场1号楼A区三层第1室","phone":"电话:18293102220"},{"name":"信达电竞中心","address":"宝兴庄68号","phone":"电话:15117229223"},{"name":"乔木电子竞技馆","address":"和平大道98号301铺","phone":"电话:17339813942"},{"name":"胜鼎巅峰电竞馆(海鸿店)","address":"中山路131-133号海鸿大厦3层","phone":"电话:8150666"},{"name":"幻境网吧","address":"农业大学北门(万嘉商贸城向南100米)李家庄村口2楼","phone":"电话:18093199201"},{"name":"星感觉网咖","address":"皋兰路69号2层","phone":"电话:0931-8728880"},{"name":"草莓网咖","address":"金惠佳苑北门旁","phone":"电话:15002546136"},{"name":"赛博电竞","address":"保利理想城","phone":""},{"name":"杰森电竞(大名城店)","address":"大名城商业街C段","phone":""},{"name":"维多利网咖(总店)","address":"天平街55号三楼(邮电大楼地铁站A口步行270米)","phone":"电话:13993187066"},{"name":"四通电竞馆","address":"建兰路街道建兰路商业步行街与瓜州路交叉口北100米","phone":""},{"name":"星烁网咖(薇乐大道店)","address":"薇乐大道73号","phone":""},{"name":"胜鼎巅峰电竞馆(中环广场店)","address":"张掖路81号（中环广场B塔3楼3F1-B）","phone":"电话:0931-4658666"},{"name":"果果网络(金牛街店)","address":"师大西门和平路114号","phone":""},{"name":"新诺电竞馆","address":"雁北路2209号2层铺面","phone":"电话:13038724444"},{"name":"月光电竞(雁滩安居小区店)","address":"雁南路2017号","phone":""},{"name":"正大网吧(西津东路店)","address":"西津东路509号","phone":""},{"name":"豪威电竞","address":"甘肃省兰州市城关区中林路21号","phone":"电话:15293081198"},{"name":"乐享电竞馆(基业豪庭店)","address":"兰州市高新街道雁兴路3286号20楼3、4、5、6号商铺","phone":""},{"name":"逗鱼电竞(老街店)","address":"兰州市七里河区西津西路长城映河苑东南侧约250米","phone":""},{"name":"裕珑网吧(金惠大厦店)","address":"武都路337号金惠大厦二楼","phone":"电话:13919058600"},{"name":"亮彤电竞中心","address":"家滩路1235号","phone":"电话:18119426182"},{"name":"朋友网络(牌坊路店)","address":"先锋路街道庄浪东路157-5号石化幸福小区1号楼2号商铺","phone":"电话:13389400075"},{"name":"乐享电竞馆(东瓯店)","address":"嘉峪关路街道东岗东路1469附9号东瓯国际大厦3层3012-3016室","phone":"电话:18189527118/18189599922"},{"name":"熊猫电竞台球棋牌综合体(农民巷店)","address":"平凉路414号2层","phone":"电话:13321219218"},{"name":"燚界电竞","address":"甘肃省兰州市安宁区国资物业第二十九佳园(东区)382-388号","phone":"电话:17709449177"},{"name":"橙鱼电竞(火车站店)","address":"定西南路438号3层","phone":"电话:09318815639"},{"name":"星际电竞(兰州中心店)","address":"建工西路3号2层","phone":""},{"name":"百安电竞网咖(世纪广场店)","address":"世纪广场348号百安三楼","phone":""},{"name":"乐享电竞馆(东岗分店)","address":"雁儿湾路35-1号","phone":"电话:13109359918"},{"name":"遇见电竞(基业豪庭店)","address":"甘肃省兰州市城关区雁兴路3616号","phone":"电话:13893464044"},{"name":"前锋网咖(南河社区卫生服站西南)","address":"张苏滩123号","phone":"电话:0931-8510483"},{"name":"解放网咖","address":"萃英门15号附5号","phone":"电话:18693849386"},{"name":"时间之墟电竞","address":"马滩南路1070号","phone":""},{"name":"暴走熊电竞馆","address":"雁滩路雁滩乡3421号","phone":"电话:09314699961"},{"name":"尖锋时刻电竞馆(甘南路店)","address":"皋兰路街道甘南路360号(路桥音乐广场斜对面,近汽车站)","phone":""},{"name":"橙鱼电竞(西固城店)","address":"新天乐对面农副大厦4楼","phone":"电话:0931-7366646"},{"name":"巅峰电竞(万辉国际广场店)","address":"甘肃省兰州市七里河区任家庄1号","phone":"电话:15379021198"},{"name":"舒闻网咖","address":"武都路156号2层","phone":"电话:17352136686/19193134466"},{"name":"萌鱼网咖","address":"雁滩联合大学南侧兴隆滨河苑东7号楼3楼","phone":"电话:18693110022"},{"name":"布洛网咖(永昌路店)","address":"永昌北路241号","phone":"电话:13993120410"},{"name":"辰光电竞馆(南滨河东路店)","address":"滩尖子385号","phone":""},{"name":"三A电竞(步行街店)","address":"张掖路187号","phone":"电话:13893383614"},{"name":"杰森网咖(九州店)","address":"九州东环路2号天昱凤凰城B区1栋1-102商铺","phone":""},{"name":"蜗牛网咖(安宁西路店)","address":"安宁西路109号","phone":"电话:18909311177"},{"name":"半糖网咖(金昌南路店)","address":"金昌南路48-58号福泉家苑南侧20米2楼","phone":""},{"name":"盛游天境","address":"平凉路414号附4","phone":"电话:13119302406"},{"name":"皮派阁PPG电玩城(兰州国芳店)","address":"广场南路东方红广场南下沉口G层国芳超市入口左侧","phone":"电话:18552886605"},{"name":"1929·潮玩星球","address":"永昌路295号紫金大厦三楼303室","phone":"电话:18419211929"},{"name":"飞马网咖","address":"嘉峪关西路79号","phone":""},{"name":"引力网咖","address":"雁南路1700号至诚名居2楼","phone":"电话:17789639509"},{"name":"橙鱼电竞(兰炼十字店)","address":"陈坪街道","phone":"电话:18693112668"},{"name":"熊芯电竞网络空间","address":"甘肃省兰州市城关区草场街街道佛慈1929文创广场(佛慈大街店)","phone":"电话:17754927595"},{"name":"腾飞网咖","address":"晏家坪二村400号1层","phone":""},{"name":"雨竹网咖(拱星墩店)","address":"东岗东路1550号飞天家园A区西南门旁(拱星墩地铁站C口步行340米)","phone":"电话:17726903008"},{"name":"强林网咖","address":"段家滩路356号","phone":""},{"name":"悦汇电竞","address":"兰州市西固区玉门街恒大都市广场西南侧约30米","phone":""},{"name":"神话电竞(下西园)","address":"下西园菜市场2楼","phone":""},{"name":"基业豪庭网咖会所","address":"雁兴路3402号","phone":"电话:13519652439"},{"name":"糖朝网络生活馆","address":"桃海商业步行街2楼","phone":"电话:15117168368"},{"name":"逗鱼电竞","address":"兰州市城关区雁滩路金鹏大厦西北侧约30米","phone":""},{"name":"凯普乐·保龄球·碰碰车·射箭(欣大购物广场店)","address":"雁滩路3113号（欣大购物广场6楼615号）","phone":"电话:13091905060"},{"name":"奇森网咖","address":"甘肃省兰州市西固区西固中路598-1-2号","phone":"电话:13893684896"},{"name":"威尔电竞(张掖路店)","address":"甘肃省兰州市城关区张掖路街道东丽大厦","phone":"电话:18152083777"},{"name":"逗鱼电竞","address":"天水北路492号嘉盛园B区六号楼负一层商铺","phone":""},{"name":"战略先锋(任家庄直营店)","address":"敦煌路483号","phone":"电话:18093165870"},{"name":"盛游天境网咖(豪布斯卡店)","address":"甘肃省兰州市七里河区敦煌路街道兰石豪布斯卡珍园肯德基左侧、电梯上三楼","phone":""},{"name":"杰森网咖(兰大店)","address":"东岗街道东岗西路449号甘肃商业大厦东北侧一楼临街商铺","phone":"电话:0931-4525369"},{"name":"头号玩家网咖(王府井店)","address":"东岗东路1999号瑞德摩尔大西洋商城2层20-2428号（近南门）","phone":"电话:0931-8103306"},{"name":"胜鼎巅峰·电竞综合体(西站店)","address":"西站西路40号四楼","phone":"电话:09318150666"},{"name":"雄风网吧(龚家湾店)","address":"兰州龚家湾345号工业学院对面","phone":""},{"name":"名典网咖(兰州商通锅炉公司家属院西北)","address":"龚家湾路274号","phone":"电话:18293102220"},{"name":"靓仔电竞","address":"定西路237附3号一层005室","phone":"电话:13919831360"},{"name":"金环宇网吧","address":"兰州市城关区佛慈大街兰州恒大绿洲一期东北侧约140米","phone":""}]