{"data":{"src_info":[],"review":{},"share_url":"","discount":[{"price_ori":"296","item_cate":"网吧网咖","price_dis":"99","source":"cp","need_reserve":"false","type":"7","pic_info":[{"srcwidth":1280,"url":"http://store.is.autonavi.com/showpic/1bd0916825e9f949f3c0335b946d5a96","srcheight":1280}],"discount_time_end":"2099-12-31 23:59:59","discount_id_tb":"896046264264","market":"discount","discount_sold_num":"2","discount_title":"【全新升级】外卖小哥专享充99享200","discount_time_beg":"2025-03-06 00:00:00","src_type":"alipay_koubei_info","discount_priority":"35","name_cn":"口碑","discount_id":"2025030640076004000004013640"}],"pic_cover":{"url":"https://aos-comment.amap.com/B0FFITDW8F/comment/0feedback_sendimage.jpeg"},"spec":{"mining_shape":{"sp_type":"","center":"","shape_type":""}},"base":{"brand_code":"AM0107709","classify":"娱乐场所","shop_info":{"claim":1},"city_adcode":"110000","code":"110105","distance":0,"title":"娱乐休闲","city_name":"北京市","sp_mark":0,"poi_tag_has_t_tag":0,"checked":"2","tag":"体育休闲服务;娱乐场所;网吧","new_type":"080308","address":"北京市朝阳区新观堂文化大道东区A南口二楼","business":"internet_bar","importance_vip_flag":0,"std_t_tag_0_v":"网吧","telephone":"","new_keytype":"体育休闲服务;娱乐场所;网吧","cre_flag":0,"pixelx":"221109422","pixely":"101746748","navi_geometry":"116.529827,39.875038","name":"合电竞网咖王四营店)","x":"116.531622","y":"39.874794","poiid":"B0FFITDW8F","end_poi_extension":"1","poi_tag":"","geodata":{"aoi":[{"area":2230.794429,"name":"漫酒店(北京欢乐谷王四营五方桥店)","mainpoi":"B0KRAHAYDC"}]}}},"status":"1"}