{"data":{"src_info":[],"review":{},"share_url":"","pic_cover":{"url":"http://store.is.autonavi.com/showpic/14baf715d619e3066b1c5686737daaa1"},"spec":{"mining_shape":{"sp_type":"","center":"","shape_type":""}},"base":{"classify":"娱乐场所","shop_info":{"claim":0},"city_adcode":"150400","code":"150404","distance":0,"title":"娱乐休闲","city_name":"赤峰市","sp_mark":0,"poi_tag_has_t_tag":0,"checked":"2","tag":"体育休闲服务;娱乐场所;网吧","new_type":"080308","address":"赤峰市松丘陵地带内蒙古交通职业技术学院东门东25","business":"internet_bar","importance_vip_flag":0,"std_t_tag_0_v":"网吧","telephone":"","new_keytype":"体育休闲服务;娱乐场所;网吧","cre_flag":0,"pixelx":"222870769","pixely":"99372728","navi_geometry":"118.892050,42.273089","name":"天涯网吧","x":"118.892796","y":"42.271893","poiid":"B0FFG7Q9WW","end_poi_extension":"1","poi_tag":"","geodata":{"aoi":[{"area":275513.637443,"name":"内蒙古交通职技术学","mainpoi":"B0FFFZTOHS"}]}}},"status":"1"}