{"data":{"src_info":[],"review":{},"share_url":"","pic_cover":{"url":"https://aos-comment.amap.com/B0GU3MHK14/comment/1D52081F_D9ED_47CB_A2C3_0F6E1CA20645_L0_001_1500_2000_1739685444042_09814068.jpg"},"spec":{"mining_shape":{"sp_type":"","center":"","shape_type":""}},"base":{"classify":"娱乐场所","shop_info":{"claim":1},"city_adcode":"500000","code":"500112","distance":0,"title":"娱乐休闲","city_name":"重庆市","sp_mark":0,"poi_tag_has_t_tag":0,"checked":"2","tag":"体育休闲服务;娱乐场所;网吧","new_type":"080308","address":"重庆市渝北区和龙路财信城市国际商业1栋9","business":"shopping","importance_vip_flag":0,"std_t_tag_0_v":"网吧","telephone":"","new_keytype":"体育休闲服务;娱乐场所;网吧","cre_flag":0,"pixelx":"213643872","pixely":"111100971","name":"Vealense威伦斯电竞(嘉州店)","x":"106.518827","y":"29.592675","poiid":"B0GU3MHK14","end_poi_extension":"0","poi_tag":"","geodata":{"aoi":[{"area":83051.133888,"name":"加州城市花园","mainpoi":"B001701A22"},{"area":33557.059958,"name":"财信·城市国际","mainpoi":"B00178VU6D"}],"landmark":[{"count":3,"hot_info":{"distance":"871","name":"红旗河沟(地铁站)","poiid":"BV10045371"},"type":3},{"count":1,"hot_info":{"distance":"2050","name":"观音桥商圈都市旅游区","poiid":"B0FFFFJGW4"},"type":4},{"count":1,"hot_info":{"distance":"484","name":"嘉州·协信中心","poiid":"B0FFFGXGLU"},"type":9}]}}},"status":"1"}