{"data":{"src_info":[],"review":{},"share_url":"http://wb.amap.com/?p=B0J0LLQZ76%2C27.709961%2C107.035189%2C%E5%96%9C%E4%B9%90%E7%94%B5%E7%AB%9E%E9%99%B6%E5%8F%B6%E5%BA%97%2C%E9%81%B5%E4%B9%89%E5%B8%82%E7%BA%A2%E8%8A%B1%E5%B2%97%E5%8C%BA%E4%B9%8C%E6%B1%9F%E5%A4%A7%E9%81%93%E4%B8%8E%E6%92%AD%E5%B7%9E%E5%A4%A7%E9%81%93%E4%BA%A4%E5%8F%89%E5%8F%A3%E4%B8%9C20%E7%B1%B3","pic_cover":{"url":"http://store.is.autonavi.com/showpic/f7084fb23d0637d09bf56ddd76a7d0ad"},"spec":{"mining_shape":{"sp_type":"","center":"","shape_type":""}},"base":{"classify":"娱乐场所","shop_info":{"claim":1},"city_adcode":"520300","code":"520302","distance":0,"title":"娱乐休闲","city_name":"遵义市","sp_mark":0,"poi_tag_has_t_tag":0,"checked":"4","tag":"体育休闲服务;娱乐场所;网吧","new_type":"080308","address":"遵义市红花岗区乌江大道与播州大道交叉口东11米","business":"internet_bar","importance_vip_flag":0,"std_t_tag_0_v":"网吧","telephone":"13885257540","new_keytype":"体育休闲服务;娱乐场所;网吧","cre_flag":0,"pixelx":"214028950","pixely":"112699660","name":"喜乐电竞陶叶店","x":"107.034554","y":"27.710857","poiid":"B0J0LLQZ76","end_poi_extension":"0","poi_tag":"","geodata":{"aoi":[{"area":23025.69817,"name":"思乐为置地广场","mainpoi":"B0FFJMRK5K"},{"area":127122.140566,"name":"林达·阳光城","mainpoi":"B03541BMYZ"}]}}},"status":"1"}