{"data":{"src_info":[],"review":{},"share_url":"http://wb.amap.com/?p=B0HGNNJ15S%2C28.999597%2C111.909922%2C%E5%8F%8B%E7%A6%8F%E7%BD%91%E5%90%A7%2C%E5%8F%8B%E7%A6%8F%E7%BD%91%E5%90%A7","pic_cover":{"url":"http://store.is.autonavi.com/showpic/d9f754ba9a08da9f665a9a4de6456a77"},"spec":{"mining_shape":{"sp_type":"","center":"","shape_type":""}},"base":{"classify":"娱乐场所","shop_info":{"claim":1},"city_adcode":"430700","code":"430703","distance":0,"title":"娱乐休闲","city_name":"常德市","sp_mark":0,"poi_tag_has_t_tag":0,"checked":"2","tag":"体育休闲服务;娱乐场所;网吧","new_type":"080308","business":"internet_bar","importance_vip_flag":0,"std_t_tag_0_v":"网吧","telephone":"13974207812","new_keytype":"体育休闲服务;娱乐场所;网吧","cre_flag":0,"pixelx":"217663814","pixely":"111606903","name":"友福网吧","x":"111.909669","y":"29.001095","poiid":"B0HGNNJ15S","end_poi_extension":"0","poi_tag":"","geodata":{}}},"status":"1"}