{"data":{"src_info":[],"review":{},"share_url":"","pic_cover":{"url":"http://store.is.autonavi.com/showpic/e5654ea169b835a03baa6f5da436bb6f"},"spec":{"mining_shape":{"sp_type":"","center":"","shape_type":""}},"base":{"brand_code":"AM0003252","classify":"中餐厅","parent":"B0FFM561PL","shop_info":{"claim":1},"city_adcode":"520100","code":"520103","distance":0,"title":"美食畅饮","city_name":"贵阳市","sp_mark":0,"poi_tag_has_t_tag":0,"checked":"4","tag":"餐饮服务;中餐厅;中餐厅","new_type":"050100","address":"贵阳市云岩区延安西路汇金星力城69号负一层(紫林庵地铁站F口旁)","business":"internet_bar","importance_vip_flag":0,"std_t_tag_0_v":"网吧","telephone":"","new_keytype":"餐饮服务;中餐厅;中餐厅","cre_flag":0,"pixelx":"213781418","pixely":"113645042","navi_geometry":"106.702296,26.580894","name":"宜博电竞馆(贵阳星力城店)","x":"106.704040","y":"26.582547","poiid":"B0KATUKNUQ","end_poi_extension":"1","poi_tag":"","geodata":{"aoi":[{"area":3219.462541,"name":"建设大厦","mainpoi":"B03530QLVJ"},{"area":12074.718299,"name":"汇金星力城","mainpoi":"B0FFFA7RSH"},{"area":866.357623,"name":"建设大厦-西楼","mainpoi":"B0FFG1PKGQ"},{"area":9768.179466,"name":"汇金写字楼","mainpoi":"B0FFM561PL"},{"area":13660.245034,"name":"世纪汇金广场","mainpoi":"B0FFGMHI79"}],"landmark":[{"count":1,"hot_info":{"distance":"2729","name":"贵阳站","poiid":"B035301F2G"},"type":2},{"count":1,"hot_info":{"distance":"1159","name":"黔灵山公园","poiid":"B03530P3K2"},"type":4},{"count":2,"hot_info":{"distance":"692","name":"贵州大学罗汉营校区","poiid":"B035302WKY"},"type":5},{"count":3,"hot_info":{"distance":"765","name":"国贸广场(中华北路店)","poiid":"B03530PJXY"},"type":7}]}}},"status":"1"}