{"data":{"src_info":[],"review":{},"share_url":"http://wb.amap.com/?p=B0LBDGXFU3%2C42.298296%2C118.948817%2CQQ%E7%BD%91%E5%90%A7%2C%E8%B5%A4%E5%B3%B0%E5%B8%82%E7%BA%A2%E5%B1%B1%E5%8C%BA%E7%81%AB%E8%8A%B1%E5%8C%97%E8%B7%AF%E4%B8%8E%E6%98%AD%E8%8B%8F%E6%B2%B3%E5%A4%A7%E8%A1%97%E4%BA%A4%E5%8F%89%E5%8F%A3%E5%8D%97120%E7%B1%B3","spec":{"mining_shape":{"sp_type":"","center":"","shape_type":""}},"base":{"classify":"娱乐场所","shop_info":{"claim":0},"city_adcode":"150400","code":"150402","distance":0,"title":"娱乐休闲","city_name":"赤峰市","sp_mark":0,"poi_tag_has_t_tag":0,"checked":"3","tag":"体育休闲服务;娱乐场所;网吧","new_type":"080308","address":"赤峰市红山区楼火花北路与昭苏河大街交叉口南111米区","business":"internet_bar","importance_vip_flag":0,"std_t_tag_0_v":"网吧","new_keytype":"体育休闲服务;娱乐场所;网吧","cre_flag":0,"pixelx":"222912394","pixely":"99347810","name":"QQ网吧","x":"118.947995","y":"42.297699","poiid":"B0LBDGXFU3","end_poi_extension":"0","poi_tag":"","geodata":{"aoi":[{"area":58267.82425,"name":"金宇国际小区A区","mainpoi":"B0FFFH0FGK"},{"area":250570.957392,"name":"金宇国际小区","mainpoi":"B0FFH1OD10"}]}}},"status":"1"}