{"data":{"src_info":[],"review":{},"share_url":"","pic_cover":{"url":"http://store.is.autonavi.com/showpic/5eb1d1353b7e67e4e50db1ce58011ff6"},"spec":{"mining_shape":{"sp_type":"","center":"","shape_type":""}},"base":{"classify":"娱乐场所","shop_info":{"claim":0},"city_adcode":"130600","code":"130626","distance":0,"title":"娱乐休闲","city_name":"保定市","sp_mark":0,"poi_tag_has_t_tag":0,"checked":"2","tag":"体育休闲服务;娱乐场所;娱乐场所","new_type":"080300","address":"保定市定兴县燕城隽府D区北8门东134米","business":"enjoy","importance_vip_flag":0,"std_t_tag_0_v":"网吧","telephone":"","new_keytype":"体育休闲服务;娱乐场所;娱乐场所","cre_flag":0,"pixelx":"220569101","pixely":"102331860","navi_geometry":"115.805507,39.270197","name":"极点电竞","x":"115.806503","y":"39.269483","poiid":"B0I1XMPB41","end_poi_extension":"1","poi_tag":"","geodata":{"aoi":[{"area":22599.782084,"name":"燕城隽府D区","mainpoi":"B01380Q5WW"},{"area":146703.058776,"name":"燕城隽府","mainpoi":"B0FFGBI9CL"}]}}},"status":"1"}