{"data":{"src_info":[],"review":{},"share_url":"","pic_cover":{"url":"http://store.is.autonavi.com/showpic/d080ad7d10b95cf8160f09ede72ed39d"},"spec":{"mining_shape":{"sp_type":"","center":"","shape_type":""}},"base":{"classify":"娱乐场所","shop_info":{"claim":1},"city_adcode":"520100","code":"520115","distance":0,"title":"娱乐休闲","city_name":"贵阳市","sp_mark":0,"poi_tag_has_t_tag":0,"checked":"2","tag":"体育休闲服务;娱乐场所;网吧","new_type":"080308","address":"贵阳市观山湖区阳光大道北大资源梦想城第1-S3栋12层59号","business":"internet_bar","importance_vip_flag":0,"std_t_tag_0_v":"网吧","telephone":"","new_keytype":"体育休闲服务;娱乐场所;网吧","cre_flag":15,"pixelx":"213752422","pixely":"113608409","navi_geometry":"106.663522,26.626141","name":"黑小黑网咖","x":"106.665195","y":"26.624764","poiid":"B0FFKYDNEU","end_poi_extension":"1","poi_tag":"","geodata":{"aoi":[{"area":438020.796852,"name":"北大资源梦想城","mainpoi":"B0FFGPV5N1"}]}}},"status":"1"}