{"data":{"src_info":[],"review":{},"share_url":"http://wb.amap.com/?p=B020705L2S%2C31.738870%2C119.625618%2C%E5%A4%A9%E5%BA%9C%E7%94%B5%E7%AB%9E(%E4%B8%B0%E7%94%B0%E8%B7%AF%E5%BA%97)%2C%E5%B8%B8%E5%B7%9E%E5%B8%82%E9%87%91%E5%9D%9B%E5%8C%BA%E5%BC%80%E5%8F%91%E5%8C%BA%E5%8D%8E%E7%9B%9B%E6%96%B0%E6%9D%91625%E5%8F%B7","pic_cover":{"url":"http://store.is.autonavi.com/showpic/52eeb59680d71ccff50996b004640b49"},"spec":{"mining_shape":{"sp_type":"","center":"","shape_type":""}},"base":{"classify":"娱乐场所","shop_info":{"claim":0},"city_adcode":"320400","code":"320413","distance":0,"title":"娱乐休闲","city_name":"常州市","sp_mark":0,"poi_tag_has_t_tag":0,"checked":"2","tag":"体育休闲服务;娱乐场所;网吧","new_type":"080308","address":"常州市金坛区开发区华盛新村632号","business":"internet_bar","importance_vip_flag":0,"std_t_tag_0_v":"网吧","new_keytype":"体育休闲服务;娱乐场所;网吧","cre_flag":0,"pixelx":"223417054","pixely":"109239132","navi_geometry":"119.624993,31.739624","name":"天府电竞(丰田路店)","x":"119.626487","y":"31.739734","poiid":"B020705L2S","end_poi_extension":"1","poi_tag":"","geodata":{"aoi":[{"area":170338.830454,"name":"金江苑一村","mainpoi":"B02070RH4A"},{"area":18517.520474,"name":"金江苑一村四区","mainpoi":"B0I62CI23Y"}]}}},"status":"1"}