{"data":{"src_info":[],"review":{},"share_url":"","pic_cover":{"url":"http://store.is.autonavi.com/showpic/6ff051421b769c496053b5f119d15f30"},"spec":{"mining_shape":{"sp_type":"","center":"","shape_type":""}},"base":{"classify":"体育休闲服务场所","shop_info":{"claim":0},"city_adcode":"430700","code":"430726","distance":0,"city_name":"常德市","sp_mark":0,"poi_tag_has_t_tag":0,"checked":"2","tag":"体育休闲服务;体育休闲服务场所;体育休闲服务场所","new_type":"080000","address":"常德市石门县楚江镇宝峰欣城9栋","business":"other","std_t_tag_0_v":"网吧","importance_vip_flag":0,"telephone":"","new_keytype":"体育休闲服务;体育休闲服务场所;体育休闲服务场所","cre_flag":7,"pixelx":"217280118","pixely":"111108212","name":"鑫瑞网咖(暂停营业)","x":"111.394620","y":"29.582313","poiid":"B0FFIQF8L2","end_poi_extension":"0","poi_tag":"","geodata":{"aoi":[{"area":34185.599719,"name":"宝峰欣城","mainpoi":"B0FFHWOQF5"}]}}},"status":"1"}