{"data":{"src_info":[],"review":{},"share_url":"","pic_cover":{"url":"http://store.is.autonavi.com/showpic/5ade03c438e3647c74979ac45ab72c62"},"spec":{"mining_shape":{"sp_type":"","center":"","shape_type":""}},"base":{"classify":"娱乐场所","shop_info":{"claim":0},"city_adcode":"520200","code":"520281","distance":0,"title":"娱乐休闲","city_name":"六盘水市","sp_mark":0,"poi_tag_has_t_tag":0,"checked":"2","tag":"体育休闲服务;娱乐场所;网吧","new_type":"080308","address":"六盘水市盘州市油桐驿站酒店3层","business":"internet_bar","importance_vip_flag":0,"std_t_tag_0_v":"网吧","telephone":"","new_keytype":"体育休闲服务;娱乐场所;网吧","cre_flag":0,"pixelx":"212152384","pixely":"114329791","navi_geometry":"104.519099,25.758633","name":"速7网咖","x":"104.518131","y":"25.758116","poiid":"B0I0BHBJRS","end_poi_extension":"1","poi_tag":"","geodata":{"aoi":[{"area":651.297212,"name":"盘州市泊庭酒店","mainpoi":"B0I0AD4HWX"}]}}},"status":"1"}