{"data":{"src_info":[],"review":{},"share_url":"","pic_cover":{"url":"http://store.is.autonavi.com/showpic/5b065a3524a82d18dceab73440e04fea"},"spec":{"mining_shape":{"sp_type":"","center":"","shape_type":""}},"base":{"classify":"娱乐场所","parent":"B0207049G1","shop_info":{"claim":0},"city_adcode":"320400","code":"320481","distance":0,"title":"娱乐休闲","city_name":"常州市","sp_mark":0,"poi_tag_has_t_tag":0,"checked":"2","tag":"体育休闲服务;娱乐场所;网吧","new_type":"080308","address":"常州市溧阳市世祖中路5号锦汇商业广场F5层","business":"internet_bar","importance_vip_flag":0,"std_t_tag_0_v":"网吧","telephone":"","new_keytype":"体育休闲服务;娱乐场所;网吧","cre_flag":0,"pixelx":"223309738","pixely":"109528942","navi_geometry":"119.482304,31.406715","name":"嘟嘟电竞(锦汇广场店)","x":"119.481609","y":"31.405786","poiid":"B0KR4YYJDR","end_poi_extension":"1","poi_tag":"","geodata":{"aoi":[{"area":19698.436939,"name":"锦汇休闲广场","mainpoi":"B0FFGZNOGK"},{"area":65053.867575,"name":"锦汇商业广场","mainpoi":"B0207049G1"},{"area":15989.427553,"name":"大润发(溧阳店)","mainpoi":"B0207049G0"}]}}},"status":"1"}