{"data":{"src_info":[],"review":{},"share_url":"","pic_cover":{"url":"http://store.is.autonavi.com/showpic/7d85492736932e33069ba319ed526b8f"},"spec":{"mining_shape":{"sp_type":"","center":"","shape_type":""}},"base":{"classify":"娱乐场所","shop_info":{"claim":0},"city_adcode":"820000","code":"820001","distance":0,"title":"娱乐休闲","city_name":"澳门特别行政区","sp_mark":0,"poi_tag_has_t_tag":0,"checked":"1","tag":"体育休闲服务;娱乐场所;网吧","new_type":"080308","address":"门同样行政区花地玛堂区东北大马路167号Ton Wa San Cun","business":"internet_bar","importance_vip_flag":0,"std_t_tag_0_v":"网吧","telephone":"","new_keytype":"体育休闲服务;娱乐场所;网吧","cre_flag":0,"pixelx":"218894479","pixely":"117231084","navi_geometry":"113.559265,22.202212","name":"5Cyber tatin(黑沙环海边马路)","x":"113.560003","y":"22.202906","poiid":"B073D00BQI","end_poi_extension":"1","poi_tag":"","geodata":{"aoi":[{"area":475.531059,"name":"东华新村第14","mainpoi":"B073D00BQJ"},{"area":566.806593,"name":"东华新村第12座","mainpoi":"B073D00C4A"},{"area":547.926237,"name":"东华新村第13座","mainpoi":"B073D00C4C"},{"area":12766.488369,"name":"东华新村","mainpoi":"B0FFL1AG9A"}],"landmark":[{"count":1,"hot_info":{"distance":"1647","name":"珠海站","poiid":"B0FFF2UNCN"},"type":2}]}}},"status":"1"}