{"data":{"src_info":[],"review":{},"share_url":"http://wb.amap.com/?p=B0KRBHUGLS%2C21.457061%2C109.125981%2C%E9%98%B3%E5%85%89%E7%94%B5%E7%AB%9E(%E5%AE%81%E6%98%A5%E5%9F%8E%E5%BA%97)%2C%E5%8C%97%E6%B5%B7%E5%B8%82%E6%B5%B7%E5%9F%8E%E5%8C%BA%E8%A5%BF%E5%8D%97%E5%A4%A7%E9%81%93%E4%B8%AD%E6%AE%B51%E5%8F%B7%E6%81%92%E6%98%8C%E5%9F%8E%E5%B8%82%E4%B8%BD%E6%99%AFb%E5%B9%A2%E5%95%86%E4%B8%9A%E8%A3%99%E6%A5%BC0106%E5%8F%B7%E5%95%86%E9%93%BA%E7%AC%AC%E4%B8%89%E5%B1%82","pic_cover":{"url":"https://aos-comment.amap.com/B0KRBHUGLS/comment/F5EA6ED9_6932_418E_8F89_7DAD39C8A6C7_L0_001_564_359_1732034328224_51369302.jpg"},"spec":{"mining_shape":{"sp_type":"","center":"","shape_type":""}},"base":{"classify":"娱乐场所","shop_info":{"claim":1},"city_adcode":"450500","code":"450502","distance":0,"title":"娱乐休闲","city_name":"北海市","sp_mark":0,"poi_tag_has_t_tag":0,"checked":"4","tag":"体育休闲服务;娱乐场所;网吧","new_type":"080308","address":"北海市海城区西南大道中段3号恒昌城市丽景b幢商业裙楼114号商铺第三层","business":"internet_bar","importance_vip_flag":0,"std_t_tag_0_v":"网吧","telephone":"19897491123","new_keytype":"体育休闲服务;娱乐场所;网吧","cre_flag":0,"pixelx":"215587957","pixely":"117830530","navi_geometry":"109.126568,21.456292","name":"阳光电竞(宁春城店)","x":"109.126810","y":"21.456407","poiid":"B0KRBHUGLS","end_poi_extension":"1","poi_tag":"","geodata":{"aoi":[{"area":23316.143489,"name":"恒昌城市丽景","mainpoi":"B030B0MIDZ"}],"landmark":[{"count":1,"hot_info":{"distance":"394","name":"北海站","poiid":"B030B00BSB"},"type":2},{"count":1,"hot_info":{"distance":"1301","name":"北海·海洋之窗","poiid":"B030B00FR5"},"type":4}]}}},"status":"1"}