{"data":{"src_info":[],"review":{},"share_url":"","pic_cover":{"url":"https://aos-comment.amap.com/B0FFGVVXZ9/comment/content_media_external_images_media_121746_1730356737921_54041648.jpg"},"spec":{"mining_shape":{"sp_type":"","center":"","shape_type":""}},"base":{"classify":"娱乐场所","shop_info":{"claim":0},"city_adcode":"430100","code":"430102","distance":0,"title":"娱乐休闲","city_name":"长沙市","sp_mark":0,"poi_tag_has_t_tag":0,"checked":"2","tag":"体育休闲服务;娱乐场所;网吧","new_type":"080308","address":"长沙市芙蓉区人民东路304号延年世嘉酒店10层西","business":"internet_bar","importance_vip_flag":0,"std_t_tag_0_v":"网吧","telephone":"","new_keytype":"体育休闲服务;娱乐场所;网吧","cre_flag":0,"pixelx":"218504979","pixely":"112298839","navi_geometry":"113.038568,28.185533","name":"新亮点网咖","x":"113.038636","y":"28.183888","poiid":"B0FFGVVXZ9","end_poi_extension":"3","poi_tag":"","geodata":{"aoi":[{"area":60468.957998,"name":"世嘉·国际华城","mainpoi":"B02DB05NDU"}],"landmark":[{"count":1,"hot_info":{"distance":"2579","name":"长沙站","poiid":"B02DB0696H"},"type":2},{"count":2,"hot_info":{"distance":"969","name":"万家丽广场(地铁站)","poiid":"BV10230974"},"type":3},{"count":1,"hot_info":{"distance":"789","name":"旺德府国际大厦","poiid":"B02DB0U57W"},"type":9}]}}},"status":"1"}