{"data":{"src_info":[],"review":{},"share_url":"http://wb.amap.com/?p=B0G3LDH11M%2C26.638869%2C106.814414%2C%E6%98%9F%E7%BE%BD%E8%BF%9E%E9%94%81%E8%81%9A%E6%97%B6%E5%85%89%E5%BA%97%2C%E8%B4%B5%E9%98%B3%E5%B8%82%E4%B9%8C%E5%BD%93%E5%8C%BA%E4%B8%80%E7%BB%84","pic_cover":{"url":"http://store.is.autonavi.com/showpic/9703b6a2996b826759ce5355e7670f75"},"spec":{"mining_shape":{"sp_type":"","center":"","shape_type":""}},"base":{"brand_code":"AM0083224","classify":"娱乐场所","shop_info":{"claim":1},"city_adcode":"520100","code":"520112","distance":0,"title":"娱乐休闲","city_name":"贵阳市","sp_mark":0,"poi_tag_has_t_tag":0,"checked":"2","tag":"体育休闲服务;娱乐场所;网吧","new_type":"080308","address":"贵阳市乌当区一组","business":"internet_bar","importance_vip_flag":0,"std_t_tag_0_v":"网吧","telephone":"18153170818","new_keytype":"体育休闲服务;娱乐场所;网吧","cre_flag":0,"pixelx":"213864328","pixely":"113597437","navi_geometry":"106.815123,26.639632","name":"星羽连锁聚时光店","x":"106.814572","y":"26.640332","poiid":"B0G3LDH11M","end_poi_extension":"1","poi_tag":"","geodata":{"aoi":[{"area":762.172094,"name":"东凯悦假日酒店","mainpoi":"B0FFFHBYOA"}]}}},"status":"1"}