{"data":{"src_info":[],"review":{},"share_url":"","pic_cover":{"url":"http://store.is.autonavi.com/showpic/9eee84bdec0d71813db62c2d9beb86d6"},"spec":{"mining_shape":{"sp_type":"","center":"","shape_type":""}},"base":{"brand_code":"AM0000790","classify":"娱乐场所","shop_info":{"claim":0},"city_adcode":"340800","code":"340811","distance":0,"title":"娱乐休闲","city_name":"安庆市","sp_mark":0,"poi_tag_has_t_tag":0,"checked":"2","tag":"体育休闲服务;娱乐场所;网吧","new_type":"080308","address":"安庆市宜区通和别东门南83米","business":"internet_bar","importance_vip_flag":0,"std_t_tag_0_v":"网吧","telephone":"","new_keytype":"体育休闲服务;娱乐场所;网吧","cre_flag":0,"pixelx":"221514301","pixely":"110271913","navi_geometry":"117.075272,30.554053","name":"风蝶网咖(聚分)","x":"117.074643","y":"30.554171","poiid":"B0FFH49FVW","end_poi_extension":"1","poi_tag":"","geodata":{"aoi":[{"area":13047.236402,"name":"通和别院","mainpoi":"B022C05W87"},{"area":53123.844067,"name":"三角花园","mainpoi":"B0FFGA8S6F"}],"landmark":[{"count":1,"hot_info":{"distance":"902","name":"安庆站","poiid":"B022C05XSG"},"type":2}]}}},"status":"1"}