{"data":{"src_info":[],"review":{},"share_url":"http://wb.amap.com/?p=B0KK9CT6IT%2C43.864641%2C125.262728%2C%E9%91%AB%E5%BF%83%E7%94%B5%E7%AB%9E(%E4%B8%87%E6%B2%85%E5%BA%97)%2C%E9%95%BF%E6%98%A5%E5%B8%82%E7%BB%BF%E5%9B%AD%E5%8C%BA%E6%98%A5%E6%99%93%E8%A1%97%E4%B8%8E%E4%B8%9C%E9%A3%8E%E5%A4%A7%E8%A1%97890%E5%8F%B7","pic_cover":{"url":"http://store.is.autonavi.com/showpic/c9c6fe88631d3a72e364e58fb765ba5d"},"spec":{"mining_shape":{"sp_type":"","center":"","shape_type":""}},"base":{"classify":"体育休闲服务场所","shop_info":{"claim":1},"city_adcode":"220100","code":"220106","distance":0,"city_name":"长春市","sp_mark":0,"poi_tag_has_t_tag":0,"checked":"4","tag":"体育休闲服务;体育休闲服务场所;体育休闲服务场所","new_type":"080000","address":"长春市绿园区春晓街与东风大街888号","business":"other","std_t_tag_0_v":"网吧","importance_vip_flag":0,"telephone":"18946796866","new_keytype":"体育休闲服务;体育休闲服务场所;体育休闲服务场所","cre_flag":0,"pixelx":"227620388","pixely":"97748579","name":"鑫心电竞(万沅店)","x":"125.263361","y":"43.864001","poiid":"B0KK9CT6IT","end_poi_extension":"0","poi_tag":"","geodata":{"aoi":[{"area":2867.975741,"name":"万沅大厦","mainpoi":"B01AF05F8D"},{"area":1991.697854,"name":"美豪丽致酒店(长春一汽高铁西站店)","mainpoi":"B0JGLZGFZE"}],"landmark":[{"count":2,"hot_info":{"distance":"940","name":"宽平桥(地铁站)","poiid":"BV10112374"},"type":3},{"count":1,"hot_info":{"distance":"2319","name":"长影旧址博物馆","poiid":"B0FFFDRU1K"},"type":4},{"count":1,"hot_info":{"distance":"579","name":"长春市机械工业学校","poiid":"B01AF06JWO"},"type":5},{"count":1,"hot_info":{"distance":"898","name":"东方斯卡拉演艺广场","poiid":"B0FFG32G2Y"},"type":8}]}}},"status":"1"}