{"data":{"src_info":[],"review":{},"share_url":"","pic_cover":{"url":"http://store.is.autonavi.com/showpic/dfb700297e5fa2d5ac2dadb52b0c8981"},"spec":{"mining_shape":{"sp_type":"","center":"","shape_type":""}},"base":{"classify":"娱乐场所","shop_info":{"claim":0},"city_adcode":"520100","code":"520115","distance":0,"title":"娱乐休闲","city_name":"贵阳市","sp_mark":0,"poi_tag_has_t_tag":0,"checked":"2","tag":"体育休闲服务;娱乐场所;网吧","new_type":"080308","address":"贵阳市观山区翁路与金华新街路口南5米","business":"internet_bar","importance_vip_flag":0,"std_t_tag_0_v":"网吧","telephone":"","new_keytype":"体育休闲服务;娱乐场所;网吧","cre_flag":0,"pixelx":"213685027","pixely":"113648170","name":"森林网咖四号店)","x":"106.575581","y":"26.578250","poiid":"B0FFM58RFB","end_poi_extension":"0","poi_tag":"","geodata":{"aoi":[{"area":434.393816,"name":"贵阳观湘黔商务酒店","mainpoi":"B0FFJMEM18"}]}}},"status":"1"}