{"data":{"src_info":[],"review":{},"share_url":"","pic_cover":{"url":"http://store.is.autonavi.com/showpic/356e82ab32f770aeda986212f6f6a24f"},"spec":{"mining_shape":{"sp_type":"","center":"","shape_type":""}},"base":{"classify":"娱乐场所","parent":"B0FFFPI4HV","shop_info":{"claim":0},"city_adcode":"371600","code":"371625","distance":0,"title":"娱乐休闲","city_name":"滨州市","sp_mark":0,"poi_tag_has_t_tag":0,"checked":"1","tag":"体育休闲服务;娱乐场所;网吧","new_type":"080308","address":"滨州市博兴县锦秋街道锦秋商场","business":"internet_bar","importance_vip_flag":0,"std_t_tag_0_v":"网吧","telephone":"","new_keytype":"体育休闲服务;娱乐场所;网吧","cre_flag":0,"pixelx":"222306747","pixely":"104352698","navi_geometry":"118.137960,37.138493","name":"白蓝阁网吧(世纪商城店)","x":"118.136024","y":"37.139089","poiid":"B0FFFPI5XM","end_poi_extension":"1","poi_tag":"","geodata":{}}},"status":"1"}