{"data":{"src_info":[],"review":{},"share_url":"","discount":[{"price_ori":"120","item_cate":"网吧网咖","price_dis":"53.8","source":"cp","need_reserve":"false","type":"7","pic_info":[{"srcwidth":580,"url":"http://store.is.autonavi.com/showpic/cffe8f5da2a18a4a60fe8147c3d5d34a","srcheight":580}],"discount_time_end":"2099-12-31 23:59:59","discount_id_tb":"803021877028","market":"discount","discount_sold_num":"7","discount_title":"4070卓威8小时畅玩","discount_time_beg":"2024-06-05 00:00:00","src_type":"alipay_koubei_info","discount_priority":"35","name_cn":"口碑","discount_id":"2024060540076004000002985967"}],"pic_cover":{"url":"http://store.is.autonavi.com/showpic/98e2a6649e37616c466c8a2f9955a7e1"},"spec":{"mining_shape":{"sp_type":"","center":"","shape_type":""}},"base":{"classify":"娱乐场所","parent":"B019B011E8","shop_info":{"claim":1},"city_adcode":"210200","code":"210202","distance":0,"title":"娱乐休闲","city_name":"大连市","sp_mark":0,"poi_tag_has_t_tag":0,"checked":"4","tag":"体育休闲服务;娱乐场所;网吧","new_type":"080308","address":"大连市中山区友好大厦西门旁(友好广场地铁站C2口步行150米)","business":"internet_bar","importance_vip_flag":0,"std_t_tag_0_v":"网吧","telephone":"","new_keytype":"体育休闲服务;娱乐场所;网吧","cre_flag":0,"pixelx":"224919092","pixely":"102667882","navi_geometry":"121.639026,38.919654","name":"蜜菓网咖(友好大厦店)","x":"121.640709","y":"38.919867","poiid":"B0FFGH3YIH","end_poi_extension":"3","poi_tag":"","geodata":{"aoi":[{"area":5538.788503,"name":"友好大厦","mainpoi":"B019B011E8"}],"landmark":[{"count":1,"hot_info":{"distance":"523","name":"大连站","poiid":"B019B0AEL6"},"type":2},{"count":4,"hot_info":{"distance":"949","name":"大连火车站(地铁站)","poiid":"BV10101895"},"type":3},{"count":6,"hot_info":{"distance":"810","name":"柏威年","poiid":"B0FFFFYHP0"},"type":7},{"count":9,"hot_info":{"distance":"219","name":"天安国际大厦","poiid":"B019B0165B"},"type":9}]}}},"status":"1"}