{"data":{"src_info":[],"review":{},"share_url":"","pic_cover":{"url":"http://store.is.autonavi.com/showpic/1c97870ffe5c3e1fbb5c42055ac9a6f7"},"spec":{"mining_shape":{"sp_type":"4000","shape":"115.89311,39.394275;115.893279,39.394244;115.893363,39.39451;115.893193,39.394541;115.89311,39.394275","level":19,"center":"","shape_type":"0","aoiid":"G00AOI000007NDT7"}},"base":{"classify":"娱乐场所","shop_info":{"claim":0},"city_adcode":"130600","code":"130626","distance":0,"title":"娱乐休闲","city_name":"保定市","sp_mark":0,"poi_tag_has_t_tag":0,"checked":"2","tag":"体育休闲服务;娱乐场所;网吧","new_type":"080308","address":"保定市定兴县通兴西路","business":"internet_bar","importance_vip_flag":0,"std_t_tag_0_v":"网吧","telephone":"","new_keytype":"体育休闲服务;娱乐场所;网吧","cre_flag":0,"pixelx":"220556482","pixely":"102333675","navi_geometry":"115.788272,39.265882","name":"龙泰电竞","x":"115.789192","y":"39.266945","poiid":"B0GUJUQISB","end_poi_extension":"1","poi_tag":"","geodata":{"aoi":[{"area":433.902354,"name":"龙泰电竞","mainpoi":"B0GUJUQISB"}]}}},"status":"1"}