{"data":{"src_info":[],"review":{},"share_url":"","pic_cover":{"url":"http://store.is.autonavi.com/showpic/0cdf7e4480162c0508d7188a3b018617"},"spec":{"mining_shape":{"sp_type":"","center":"","shape_type":""}},"base":{"classify":"娱乐场所","shop_info":{"claim":0},"city_adcode":"130600","code":"130627","distance":0,"title":"娱乐休闲","city_name":"保定市","sp_mark":0,"poi_tag_has_t_tag":0,"checked":"2","tag":"体育休闲服务;娱乐场所;网吧","new_type":"080308","address":"保定市唐县塔南路","business":"internet_bar","importance_vip_flag":0,"std_t_tag_0_v":"网吧","telephone":"","new_keytype":"体育休闲服务;娱乐场所;网吧","cre_flag":0,"pixelx":"219944785","pixely":"102840357","navi_geometry":"114.968076,38.738315","name":"铭畅的网络","x":"114.968652","y":"38.739305","poiid":"B0HRVXGKKA","end_poi_extension":"1","poi_tag":"","geodata":{"aoi":[{"area":1158.017947,"name":"老顽童老年公寓","mainpoi":"B0138037VI"}]}}},"status":"1"}