{"data":{"src_info":[],"review":{},"share_url":"","pic_cover":{"url":"http://store.is.autonavi.com/showpic/fd1fe0a9ff6dd05eb5794c2a18a2c763"},"spec":{"mining_shape":{"sp_type":"","center":"","shape_type":""}},"base":{"classify":"娱乐场所","shop_info":{"claim":0},"city_adcode":"520400","code":"520425","distance":0,"title":"娱乐休闲","city_name":"安顺市","sp_mark":0,"poi_tag_has_t_tag":0,"checked":"2","tag":"体育休闲服务;娱乐场所;网吧","new_type":"080308","address":"安顺市紫云苗族布依族自治县观音路与金菜园西路交叉口东南29米","business":"internet_bar","importance_vip_flag":0,"std_t_tag_0_v":"网吧","telephone":"","new_keytype":"体育休闲服务;娱乐场所;网吧","cre_flag":6,"pixelx":"213322240","pixely":"114333697","name":"七号网络","x":"106.086574","y":"25.752298","poiid":"B0FFI9ZVQW","end_poi_extension":"0","poi_tag":"","geodata":{}}},"status":"1"}