{"data":{"src_info":[],"review":{},"share_url":"http://wb.amap.com/?p=B01600MG89%2C39.440344%2C114.240317%2C%E7%A7%91%E6%B1%87%E7%BD%91%E5%90%A7(%E6%96%B0%E5%8D%8E%E8%A1%97)%2C%E5%A4%A7%E5%90%8C%E5%B8%82%E7%81%B5%E4%B8%98%E5%8E%BF%E9%9D%92%E5%B9%B4%E8%B7%AF","pic_cover":{"url":"http://store.is.autonavi.com/showpic/6aa24b334519ecaec42107b77a95dfab"},"spec":{"mining_shape":{"sp_type":"","shape":"","center":"","shape_type":""}},"base":{"classify":"娱乐场所","shop_info":{"claim":0},"city_adcode":"140200","code":"140224","distance":0,"title":"娱乐休闲","city_name":"大同市","sp_mark":0,"poi_tag_has_t_tag":0,"checked":"2","tag":"体育休闲服务;娱乐场所;网吧","new_type":"080308","address":"大同市灵丘县青年路","business":"internet_bar","importance_vip_flag":0,"std_t_tag_0_v":"网吧","new_keytype":"体育休闲服务;娱乐场所;网吧","cre_flag":0,"pixelx":"219401482","pixely":"102166619","name":"科汇网吧(新华街)","x":"114.240317","y":"39.440344","poiid":"B01600MG89","end_poi_extension":"0","poi_tag":"","geodata":{}}},"status":"1"}