{"data":{"src_info":[],"review":{},"share_url":"http://wb.amap.com/?p=B0HR6U88R6%2C31.870731%2C106.743846%2C%E9%9B%B6%E5%BA%A6%E7%94%B5%E7%AB%9E%2C%E5%B7%B4%E4%B8%AD%E5%B8%82%E5%B7%B4%E5%B7%9E%E5%8C%BA%E5%91%A8%E5%AE%B6%E8%A1%9744%E5%8F%B7(%E5%BE%B7%E7%A6%8F%E8%8A%B1%E5%9B%AD)A1%E5%B9%A2F-%E8%B4%9F2-2-1%E5%8F%B7","pic_cover":{"url":"http://store.is.autonavi.com/showpic/d136848ba8717c7d86a86b2db144973e"},"spec":{"mining_shape":{"sp_type":"","center":"","shape_type":""}},"base":{"classify":"娱乐场所","shop_info":{"claim":1},"city_adcode":"511900","code":"511902","distance":0,"title":"娱乐休闲","city_name":"巴中市","sp_mark":0,"poi_tag_has_t_tag":0,"checked":"2","tag":"体育休闲服务;娱乐场所;网吧","new_type":"080308","address":"巴中市巴州区周家街50号(德福花园)A0幢F-负3-3-3号","business":"internet_bar","importance_vip_flag":0,"std_t_tag_0_v":"网吧","new_keytype":"体育休闲服务;娱乐场所;网吧","cre_flag":0,"pixelx":"213811708","pixely":"109123432","navi_geometry":"106.744285,31.869795","name":"零度电竞","x":"106.743161","y":"31.869988","poiid":"B0HR6U88R6","end_poi_extension":"1","poi_tag":"","geodata":{"aoi":[{"area":17051.769555,"name":"德福花园","mainpoi":"B033B0P13O"}],"landmark":[{"count":1,"hot_info":{"distance":"1994","name":"巴中站","poiid":"B033B0PH7P"},"type":2}]}}},"status":"1"}