{"data":{"src_info":[],"review":{},"share_url":"http://wb.amap.com/?p=B0KR2PJ4DT%2C33.540411%2C115.792042%2C%E6%A0%91%E5%91%86%E7%86%8A%E7%94%B5%E7%AB%9E%E9%A6%86%E7%94%B5%E7%AB%9E%E9%A6%86%2C%E4%BA%B3%E5%B7%9E%E5%B8%82%E8%B0%AF%E5%9F%8E%E5%8C%BA252%E7%9C%81%E9%81%93","pic_cover":{"url":"http://store.is.autonavi.com/showpic/348eff243c82e45a585dde0fd169967a"},"spec":{"mining_shape":{"sp_type":"","center":"","shape_type":""}},"base":{"classify":"体育休闲服务场所","shop_info":{"claim":0},"city_adcode":"341600","code":"341602","distance":0,"city_name":"亳州市","sp_mark":0,"poi_tag_has_t_tag":0,"checked":"4","tag":"体育休闲服务;体育休闲服务场所;体育休闲服务场所","new_type":"080000","address":"亳州市谯城区249省道","business":"other","std_t_tag_0_v":"网吧","importance_vip_flag":0,"telephone":"19018000012","new_keytype":"体育休闲服务;体育休闲服务场所;体育休闲服务场所","cre_flag":0,"pixelx":"220558532","pixely":"107643759","name":"树呆熊电竞馆电竞馆","x":"115.791175","y":"33.540996","poiid":"B0KR2PJ4DT","end_poi_extension":"0","poi_tag":"","geodata":{"aoi":[{"area":566.488052,"name":"中国石化古城加油站","mainpoi":"B0HKH7DQA2"}]}}},"status":"1"}