{"data":{"src_info":[],"review":{},"share_url":"","pic_cover":{"url":"http://store.is.autonavi.com/showpic/8d015c6a37ea62bfd5c33616feb32cb2"},"spec":{"mining_shape":{"sp_type":"","center":"","shape_type":""}},"base":{"classify":"运动场馆","parent":"B02DB046GY","shop_info":{"claim":0},"city_adcode":"430100","code":"430111","distance":0,"title":"体育场馆","city_name":"长沙市","sp_mark":0,"poi_tag_has_t_tag":0,"checked":"2","tag":"体育休闲服务;运动场馆;台球厅","new_type":"080113|080308","address":"长沙市雨花区侯家塘街道劳动西路315号梓园大厦负一楼","business":"internet_bar","importance_vip_flag":0,"std_t_tag_0_v":"台球厅","telephone":"","new_keytype":"体育休闲服务;运动场馆;台球厅|体育休闲服务;娱乐场所;网吧","cre_flag":0,"pixelx":"218467572","pixely":"112310186","navi_geometry":"112.987286,28.170716","name":"绅士网吧台球·忆楚管理(梓园大厦店)","x":"112.987073","y":"28.170586","poiid":"B02DB106EL","end_poi_extension":"1","poi_tag":"","geodata":{"aoi":[{"area":2580.834144,"name":"兴威新嘉园","mainpoi":"B02DB04UH0"},{"area":2114.545312,"name":"梓园大厦","mainpoi":"B02DB046GY"}],"landmark":[{"count":2,"hot_info":{"distance":"522","name":"侯家塘(地铁站)","poiid":"BV10229926"},"type":3},{"count":1,"hot_info":{"distance":"1512","name":"天心阁","poiid":"B02DB03ZUX"},"type":4},{"count":3,"hot_info":{"distance":"622","name":"贺龙体育馆","poiid":"B02DB0695Q"},"type":8},{"count":1,"hot_info":{"distance":"306","name":"佳天国际","poiid":"B02DB03TRR"},"type":9}]}}},"status":"1"}