{"data":{"src_info":[],"review":{},"share_url":"","pic_cover":{"url":"http://store.is.autonavi.com/showpic/5f7733e4e9d0b20afe26b9f67fa0cd58"},"spec":{"mining_shape":{"sp_type":"","center":"","shape_type":""}},"base":{"classify":"娱乐场所","shop_info":{"claim":0},"city_adcode":"320400","code":"320481","distance":0,"title":"娱乐休闲","city_name":"常州市","sp_mark":0,"poi_tag_has_t_tag":0,"checked":"4","tag":"体育休闲服务;娱乐场所;网吧","new_type":"080308","address":"常州市溧阳市别桥镇赵匡胤镇新街6号","business":"internet_bar","importance_vip_flag":0,"std_t_tag_0_v":"网吧","telephone":"","new_keytype":"体育休闲服务;娱乐场所;网吧","cre_flag":0,"pixelx":"223237920","pixely":"109387614","navi_geometry":"119.386490,31.570349","name":"天空网吧","x":"119.387176","y":"31.569693","poiid":"B0HKPZ7A7P","end_poi_extension":"1","poi_tag":"","geodata":{}}},"status":"1"}