{"data":{"src_info":[],"review":{},"share_url":"","pic_cover":{"url":"http://store.is.autonavi.com/showpic/3b430b57d49ad652b60fa89ad1b12eb8"},"spec":{"mining_shape":{"sp_type":"","center":"","shape_type":""}},"base":{"classify":"娱乐场所","shop_info":{"claim":1},"city_adcode":"430100","code":"430105","distance":0,"title":"娱乐休闲","city_name":"长沙市","sp_mark":0,"poi_tag_has_t_tag":0,"checked":"2","tag":"体育休闲服务;娱乐场所;网吧","new_type":"080308","address":"长沙市开福区德雅路公园0号小区裙楼6层(芙蓉路湘雅路口)","business":"internet_bar","importance_vip_flag":0,"std_t_tag_0_v":"网吧","telephone":"","new_keytype":"体育休闲服务;娱乐场所;网吧","cre_flag":0,"pixelx":"218468823","pixely":"112275000","navi_geometry":"112.990108,28.213902","name":"发条网咖(东风路店)","x":"112.988603","y":"28.212159","poiid":"B0FFFZVMF7","end_poi_extension":"1","poi_tag":"","geodata":{"aoi":[{"area":13106.407594,"name":"公园9号1期","mainpoi":"B0JAYMGG58"},{"area":13771.14722,"name":"公园9号","mainpoi":"B02DB0TV2P"}],"landmark":[{"count":2,"hot_info":{"distance":"317","name":"湖南博物院","poiid":"B02DB00018"},"type":4},{"count":2,"hot_info":{"distance":"216","poiid":"B0FFI0WUS2"},"type":9}]}}},"status":"1"}