{"data":{"src_info":[],"review":{},"share_url":"","pic_cover":{"url":"http://aos-cdn-image.amap.com/sns/ugccomment/d8c06921-4bda-432d-8875-2183a6259d7c.jpg"},"spec":{"mining_shape":{"sp_type":"","center":"","shape_type":""}},"base":{"classify":"娱乐场所","shop_info":{"claim":1},"city_adcode":"130900","code":"130902","distance":0,"title":"娱乐休闲","city_name":"沧州市","sp_mark":0,"poi_tag_has_t_tag":0,"checked":"2","tag":"体育休闲服务;娱乐场所;网吧","new_type":"080308","address":"沧州市新华乡长芦北大道15号","business":"internet_bar","importance_vip_flag":0,"std_t_tag_0_v":"网吧","telephone":"","new_keytype":"体育休闲服务;娱乐场所;网吧","cre_flag":0,"pixelx":"221383266","pixely":"103245840","navi_geometry":"116.899177,38.312999","name":"千予网咖","x":"116.898323","y":"38.312628","poiid":"B0FFJMAKJJ","end_poi_extension":"1","poi_tag":"","geodata":{"aoi":[{"area":19709.076196,"name":"益民家园","mainpoi":"B0FFFEAC1F"}]}}},"status":"1"}