{"data":{"src_info":[],"review":{},"share_url":"","pic_cover":{"url":"http://store.is.autonavi.com/showpic/b54656f92cebc3e3c760726cc99bcce0"},"spec":{"mining_shape":{"sp_type":"","center":"","shape_type":""}},"base":{"brand_code":"AT0000760","classify":"娱乐场所","shop_info":{"claim":0},"city_adcode":"130600","code":"130607","distance":0,"title":"娱乐休闲","city_name":"保定市","sp_mark":0,"poi_tag_has_t_tag":0,"checked":"2","tag":"体育休闲服务;娱乐场所;网吧","new_type":"080308","address":"定市城区汉润文创园东侧5米","business":"internet_bar","importance_vip_flag":0,"std_t_tag_0_v":"网吧","telephone":"","new_keytype":"体育休闲服务;娱乐场所;网吧","cre_flag":0,"pixelx":"220222402","pixely":"102630940","navi_geometry":"115.340136,38.959012","name":"网巢网咖(宏昌北店)","x":"115.341792","y":"38.958311","poiid":"B0FFH8BP44","end_poi_extension":"1","poi_tag":"","geodata":{"aoi":[{"area":27348.489787,"name":"星河源A","mainpoi":"B0FFHOUCCW"}]}}},"status":"1"}