{"data":{"src_info":[],"review":{},"share_url":"","pic_cover":{"url":"http://store.is.autonavi.com/showpic/a54ae2543bd14ad143e514944a3926ca"},"spec":{"mining_shape":{"sp_type":"","center":"","shape_type":""}},"base":{"brand_code":"AM0007346","classify":"娱乐场所","shop_info":{"claim":1},"city_adcode":"520400","code":"520424","distance":0,"title":"娱乐休闲","city_name":"安顺市","sp_mark":0,"poi_tag_has_t_tag":0,"checked":"2","tag":"体育休闲服务;娱乐场所;网吧","new_type":"080308","address":"安顺市武山布依族苗族自治县关索大道龙潭街道大岩新区兴欣佳苑B幢3单元7层","business":"internet_bar","importance_vip_flag":0,"std_t_tag_0_v":"网吧","telephone":"","new_keytype":"体育休闲服务;娱乐场所;网吧","cre_flag":0,"pixelx":"212976863","pixely":"114182395","navi_geometry":"105.624662,25.936170","name":"勇士电竞旗舰店","x":"105.624178","y":"25.935690","poiid":"B0JU6LP1LD","end_poi_extension":"1","poi_tag":"","geodata":{"aoi":[{"area":3830.514423,"name":"兴欣佳苑","mainpoi":"B0FFG0JAS4"}]}}},"status":"1"}