{"data":{"src_info":[],"review":{},"share_url":"","pic_cover":{"url":"http://store.is.autonavi.com/showpic/e3a772f508281d57c103bdde06e4b986"},"spec":{"mining_shape":{"sp_type":"","center":"","shape_type":""}},"base":{"classify":"娱乐场所","shop_info":{"claim":1},"city_adcode":"520100","code":"520115","distance":0,"title":"娱乐休闲","city_name":"贵阳市","sp_mark":0,"poi_tag_has_t_tag":0,"checked":"2","tag":"体育休闲服务;娱乐场所;网吧","new_type":"080308","business":"internet_bar","importance_vip_flag":0,"std_t_tag_0_v":"网吧","telephone":"","new_keytype":"体育休闲服务;娱乐场所;网吧","cre_flag":0,"pixelx":"213738326","pixely":"113624746","navi_geometry":"106.645029,26.607029","name":"小魔虎电竞(二进制店)","x":"106.644568","y":"26.606766","poiid":"B0K0OZLVS6","end_poi_extension":"1","poi_tag":"","geodata":{"aoi":[{"area":61333.927694,"name":"贵阳世纪城龙凯苑北区","mainpoi":"B03530OXWP"},{"area":99405.190316,"name":"贵阳世纪城龙凯苑","mainpoi":"B0FFF9SV52"},{"area":2184025.492415,"name":"贵阳世纪城","mainpoi":"B035302WI9"}],"landmark":[{"count":1,"hot_info":{"distance":"2945","name":"贵阳北站","poiid":"B0FFFR0KU5"},"type":2},{"count":1,"hot_info":{"distance":"302","name":"贵州工业职业技术学院","poiid":"B035302R9W"},"type":5},{"count":2,"hot_info":{"distance":"581","name":"世纪金源国际财富中心","poiid":"B03530P32V"},"type":9}]}}},"status":"1"}