{"data":{"src_info":[],"review":{},"share_url":"http://wb.amap.com/?p=B0J2PY2WF4%2C28.242846%2C113.102126%2C%E9%A9%B0%E9%A3%9E%E7%BD%91%E5%92%96%2C%E9%95%BF%E6%B2%99%E5%B8%82%E9%95%BF%E6%B2%99%E5%8E%BF%E6%98%9F%E6%B2%99%E8%A1%97%E9%81%93%E4%B8%9C%E5%9B%9B%E8%B7%AF%E5%AE%B6%E5%92%8C%E9%99%A28%E6%A0%8B112-117%E5%95%86%E9%93%BA","pic_cover":{"url":"http://store.is.autonavi.com/showpic/03ac58c2cb7984f719b272b0bb4d7031"},"spec":{"mining_shape":{"sp_type":"","center":"","shape_type":""}},"base":{"classify":"娱乐场所","shop_info":{"claim":0},"city_adcode":"430100","code":"430121","distance":0,"title":"娱乐休闲","city_name":"长沙市","sp_mark":0,"poi_tag_has_t_tag":0,"checked":"2","tag":"体育休闲服务;娱乐场所;网吧","new_type":"080308","address":"长沙市长沙县星沙街道东四路家和院7栋112-111商铺","business":"internet_bar","importance_vip_flag":0,"std_t_tag_0_v":"网吧","telephone":"13203113781","new_keytype":"体育休闲服务;娱乐场所;网吧","cre_flag":0,"pixelx":"218552786","pixely":"112249734","name":"驰飞网咖","x":"113.102918","y":"28.242058","poiid":"B0J2PY2WF4","end_poi_extension":"0","poi_tag":"","geodata":{"aoi":[{"area":72411.57751,"name":"家和院","mainpoi":"B02DB0UFG2"}]}}},"status":"1"}