{"data":{"src_info":[],"review":{},"share_url":"http://wb.amap.com/?p=B0FFGZ3EVK%2C36.937470%2C117.710147%2C%E9%BE%99%E5%9F%8E%E7%BD%91%E5%90%A7%2C%E6%BB%A8%E5%B7%9E%E5%B8%82%E9%82%B9%E5%B9%B3%E5%B8%82%E9%9F%A9%E5%BA%97%E9%95%87%E5%B0%8F%E7%8E%8B%E9%A9%BC%E6%9D%91%E7%8E%8B%E6%89%98%E8%B7%AF%E5%8F%A3%E8%A5%BF","pic_cover":{"url":"http://store.is.autonavi.com/showpic/ff98ddefc2fa91810aa2ab1057f85019"},"spec":{"mining_shape":{"sp_type":"","center":"","shape_type":""}},"base":{"classify":"娱乐场所","shop_info":{"claim":0},"city_adcode":"371600","code":"371681","distance":0,"title":"娱乐休闲","city_name":"滨州市","sp_mark":0,"poi_tag_has_t_tag":0,"checked":"2","tag":"体育休闲服务;娱乐场所;网吧","new_type":"080308","address":"滨州市邹平市韩店镇小王驼村王托路口西","business":"internet_bar","importance_vip_flag":0,"std_t_tag_0_v":"网吧","new_keytype":"体育休闲服务;娱乐场所;网吧","cre_flag":0,"pixelx":"221988775","pixely":"104541510","navi_geometry":"117.710649,36.937888","name":"龙城网吧","x":"117.710764","y":"36.938376","poiid":"B0FFGZ3EVK","end_poi_extension":"1","poi_tag":"","geodata":{}}},"status":"1"}