{"data":{"src_info":[],"review":{},"share_url":"","pic_cover":{"url":"http://store.is.autonavi.com/showpic/c3e501a94dc07c8502887082a3002a3a"},"spec":{"mining_shape":{"sp_type":"","center":"","shape_type":""}},"base":{"classify":"体育休闲服务场所","parent":"B02DB0ZNQB","shop_info":{"claim":1},"city_adcode":"430100","code":"430121","distance":0,"city_name":"长沙市","sp_mark":0,"poi_tag_has_t_tag":0,"checked":"2","tag":"体育休闲服务;体育休闲服务场所;体育休闲服务场所","new_type":"080000","address":"长沙市长沙县青翠路6金·时代中心6层","business":"internet_bar","std_t_tag_0_v":"网吧","importance_vip_flag":0,"telephone":"","new_keytype":"体育休闲服务;体育休闲服务场所;体育休闲服务场所","cre_flag":0,"pixelx":"218532210","pixely":"112261315","navi_geometry":"113.073704,28.229681","name":"虫电竞(金科店)","x":"113.072961","y":"28.229170","poiid":"B0G39RP2KB","end_poi_extension":"3","poi_tag":"","geodata":{"aoi":[{"area":2028.239012,"name":"科中企业总部大厦","mainpoi":"B0FFL2XO68"},{"area":83422.238238,"name":"金科·时代中心","mainpoi":"B02DB0ZNQB"}],"landmark":[{"count":2,"hot_info":{"distance":"2099","name":"长沙世界之窗","poiid":"B02DB068W5"},"type":4},{"count":1,"hot_info":{"distance":"190","poiid":"B0FFG2Q5EG"},"type":9}]}}},"status":"1"}